vlm_rprimo/__init__.py
vlm_rprimo/vlm_rprimo.py
vlm_rprimo-1.0.dist-info/LICENSE
vlm_rprimo-1.0.dist-info/METADATA
vlm_rprimo-1.0.dist-info/WHEEL
vlm_rprimo-1.0.dist-info/top_level.txt
vlm_rprimo-1.0.dist-info/RECORD
